PCRinSilico/PCRinSilico.py
PCRinSilico/__init__.py
PCRinSilico-1.1.3.dist-info/METADATA
PCRinSilico-1.1.3.dist-info/WHEEL
PCRinSilico-1.1.3.dist-info/entry_points.txt
PCRinSilico-1.1.3.dist-info/top_level.txt
PCRinSilico-1.1.3.dist-info/RECORD
