Metadata-Version: 2.1
Name: PCRinSilico
Version: 1.1.3
Summary: In silico PCR tool
Home-page: https://github.com/SemiQuant/inSilicoPCR
Author: Jason D Limberis
Author-email: Jason.Limberis@ucsf.edu
License: MIT
Keywords: PCR,in silico PCR
Platform: UNKNOWN
Classifier: Programming Language :: Python :: 3
Classifier: License :: OSI Approved :: MIT License
Classifier: Operating System :: OS Independent
Requires-Dist: pandas
Requires-Dist: biopython
